setup.py
mtweets/__init__.py
mtweets/api.py
mtweets/streaming.py
mtweets/utils.py
mtweets.egg-info/PKG-INFO
mtweets.egg-info/SOURCES.txt
mtweets.egg-info/dependency_links.txt
mtweets.egg-info/requires.txt
mtweets.egg-info/top_level.txt