Metadata-Version: 1.0
Name: mtweets
Version: 0.4
Summary: An easy (and up to date) way to access Twitter data with Python.
Home-page: http://github.com/carlitux/mtweets
Author: Luis Carlos Cruz
Author-email: carlitos.kyo@gmail.com
License: MIT License
Keywords: twitter search api tweet twython mtweets
Platform: UNKNOWN
Classifier: Development Status :: 4 - Beta
Classifier: Intended Audience :: Developers
Classifier: License :: OSI Approved :: MIT License
Classifier: Topic :: Software Development :: Libraries :: Python Modules
Classifier: Topic :: Communications :: Chat
Classifier: Topic :: Internet
